abqcy/__init__.py
abqcy/__main__.py
abqcy/_version.py
abqcy/cli.py
abqcy/subs.py
abqcy/version.py
abqcy-0.0.5.dist-info/LICENSE
abqcy-0.0.5.dist-info/METADATA
abqcy-0.0.5.dist-info/WHEEL
abqcy-0.0.5.dist-info/entry_points.txt
abqcy-0.0.5.dist-info/top_level.txt
abqcy-0.0.5.dist-info/RECORD
