Metadata-Version: 2.1
Name: abqcy
Version: 0.0.5
Summary: Write Abaqus Subroutines in Python
Author-email: WANG Hailin <hailin.wang@connect.polyu.hk>
Project-URL: GitHub, https://github.com/haiiliin/abqcy/
Project-URL: PyPI, https://pypi.org/project/abqcy/
Project-URL: Read the Docs, https://readthedocs.org/projects/abqcy
Project-URL: Documentation, https://docs.abqcy.com/
Project-URL: Bug Report, https://github.com/haiiliin/abqcy/issues/
Classifier: Programming Language :: Python
Classifier: Programming Language :: Python :: 3
Classifier: Programming Language :: Python :: 3.7
Classifier: Programming Language :: Python :: 3.8
Classifier: Programming Language :: Python :: 3.9
Classifier: Programming Language :: Python :: 3.10
Classifier: Programming Language :: Python :: 3.11
Classifier: Programming Language :: Python :: Implementation :: PyPy
Classifier: License :: OSI Approved :: MIT License
Classifier: Operating System :: OS Independent
Requires-Python: >=3.7
License-File: LICENSE
Requires-Dist: abqpy
Requires-Dist: cython
Requires-Dist: fire
Requires-Dist: python-dotenv
Provides-Extra: dev
Requires-Dist: black ; extra == 'dev'
Requires-Dist: coverage ; extra == 'dev'
Requires-Dist: coveralls ; extra == 'dev'
Requires-Dist: isort ; extra == 'dev'
Requires-Dist: matplotlib ; extra == 'dev'
Requires-Dist: numpy ; extra == 'dev'
Requires-Dist: pandas ; extra == 'dev'
Requires-Dist: pre-commit ; extra == 'dev'
Requires-Dist: pytest ; extra == 'dev'
Requires-Dist: pytest-cov ; extra == 'dev'
Requires-Dist: pytest-mpl ; extra == 'dev'
Requires-Dist: tox ; extra == 'dev'
Provides-Extra: docs
Requires-Dist: myst-parser ; extra == 'docs'
Requires-Dist: sphinx ; extra == 'docs'
Requires-Dist: sphinx-autoapi ; extra == 'docs'
Requires-Dist: sphinx-autodoc-typehints ; extra == 'docs'
Requires-Dist: sphinx-codeautolink ; extra == 'docs'
Requires-Dist: sphinx-copybutton ; extra == 'docs'
Requires-Dist: sphinx-design ; extra == 'docs'
Requires-Dist: sphinx-hoverxref ; extra == 'docs'
Requires-Dist: sphinx-inline-tabs ; extra == 'docs'
Requires-Dist: sphinx-rtd-theme ; extra == 'docs'
Requires-Dist: sphinxcontrib-programoutput ; extra == 'docs'
